log2telegram/__init__.py
log2telegram/cron.py
log2telegram/main.py
log2telegram/utils.py
log2telegram-0.6.5.dist-info/METADATA
log2telegram-0.6.5.dist-info/WHEEL
log2telegram-0.6.5.dist-info/entry_points.txt
log2telegram-0.6.5.dist-info/top_level.txt
log2telegram-0.6.5.dist-info/RECORD
